pycelsiusnetwork/__init__.py
pycelsiusnetwork/celsius.py
pycelsiusnetwork-0.3.0.dist-info/LICENSE
pycelsiusnetwork-0.3.0.dist-info/METADATA
pycelsiusnetwork-0.3.0.dist-info/WHEEL
pycelsiusnetwork-0.3.0.dist-info/top_level.txt
pycelsiusnetwork-0.3.0.dist-info/RECORD
